vmcp/__init__.py
vmcp/events.py
vmcp/facades.py
vmcp/protocol.py
vmcp/typing.py
vmcp/osc/__init__.py
vmcp/osc/osc.py
vmcp/osc/typing.py
vmcp/osc/backend/__init__.py
vmcp/osc/backend/typing.py
vmcp/osc/backend/osc4py3/__init__.py
vmcp/osc/backend/osc4py3/_as_allthreads.py
vmcp/osc/backend/osc4py3/_as_comthreads.py
vmcp/osc/backend/osc4py3/_as_eventloop.py
vmcp/osc/backend/osc4py3/common.py
vmcp/osc/channel/__init__.py
vmcp/osc/channel/common.py
vmcp/osc/channel/receiver.py
vmcp/osc/channel/sender.py
vmcp-1.0.6.dist-info/LICENSE.txt
vmcp-1.0.6.dist-info/METADATA
vmcp-1.0.6.dist-info/WHEEL
vmcp-1.0.6.dist-info/top_level.txt
vmcp-1.0.6.dist-info/RECORD
