Metadata-Version: 2.1
Name: vmcp
Version: 1.0.6
Summary: Virtual Motion Capture protocol package
Author-email: Vivien Richter <vivien-richter@outlook.de>
License: AGPL-3.0-or-later
Project-URL: homepage, https://codeberg.org/vivi90/python-vmcp
Project-URL: documentation, https://vivi90.codeberg.page/python-vmcp
Project-URL: repository, https://codeberg.org/vivi90/python-vmcp
Project-URL: tracker, https://codeberg.org/vivi90/python-vmcp/issues
Keywords: VMC,protocol,MR,VR,XR,AR
Classifier: Programming Language :: Python
Classifier: Programming Language :: Python :: 3
Classifier: Programming Language :: Python :: 3.10
Classifier: Topic :: Software Development :: Libraries :: Python Modules
Classifier: Topic :: Internet
Classifier: Topic :: Multimedia :: Graphics :: Capture
Classifier: License :: OSI Approved :: GNU Affero General Public License v3 or later (AGPLv3+)
Classifier: Operating System :: OS Independent
Classifier: Development Status :: 5 - Production/Stable
Requires-Python: >=3.10
License-File: LICENSE.txt
Provides-Extra: dev
Requires-Dist: pylint ; extra == 'dev'
Requires-Dist: mypy ; extra == 'dev'
Requires-Dist: pytest ; extra == 'dev'
Requires-Dist: bandit ; extra == 'dev'
Requires-Dist: black ; extra == 'dev'
Requires-Dist: flake8 ; extra == 'dev'
Requires-Dist: pydocstyle ; extra == 'dev'
Provides-Extra: docu
Requires-Dist: pdoc ; extra == 'docu'
Requires-Dist: setuptools-scm ; extra == 'docu'
Provides-Extra: osc4py3
Requires-Dist: osc4py3 (<1.0.4,>=1.0.1) ; extra == 'osc4py3'
Provides-Extra: tests
Requires-Dist: pylint ; extra == 'tests'
Requires-Dist: mypy ; extra == 'tests'
Requires-Dist: pytest ; extra == 'tests'
Requires-Dist: bandit ; extra == 'tests'
